LICENSE
README.md
pyproject.toml
setup.py
src/mathematic_brojas/__init__.py
src/mathematic_brojas/aritmatika.py
src/mathematic_brojas/bangun_ruang.py
src/mathematic_package_MRBrojas.egg-info/PKG-INFO
src/mathematic_package_MRBrojas.egg-info/SOURCES.txt
src/mathematic_package_MRBrojas.egg-info/dependency_links.txt
src/mathematic_package_MRBrojas.egg-info/top_level.txt