Metadata-Version: 2.1
Name: mathematic-package-MRBrojas
Version: 1.1.0
Summary: Matematika untuk python
Home-page: https://github.com/pypa/sampleproject
Author: MRBrojas
Author-email: mochradja@gmail.com
License: UNKNOWN
Project-URL: Bug Tracker, https://github.com/pypa/sampleproject/issues
Platform: UNKNOWN
Classifier: Programming Language :: Python :: 3
Classifier: License :: OSI Approved :: MIT License
Classifier: Operating System :: OS Independent
Requires-Python: >=3.6
License-File: LICENSE
